Metadata-Version: 2.1
Name: odoo9-addon-l10n-es-aeat-mod111
Version: 9.0.1.1.1.99.dev9
Summary: AEAT modelo 111
Home-page: https://github.com/OCA/l10n-spain
Author: AvanzOSC,RGB Consulting SL,Tecnativa,Odoo Community Association (OCA)
Author-email: support@odoo-community.org
License: AGPL-3
Platform: UNKNOWN
Classifier: Programming Language :: Python
Classifier: Framework :: Odoo
Classifier: Framework :: Odoo :: 9.0
Classifier: License :: OSI Approved :: GNU Affero General Public License v3
Requires-Python: ~=2.7
Requires-Dist: odoo9-addon-l10n-es-aeat
Requires-Dist: odoo (<9.1a,>=9.0a)
